ai_assistant/__init__.py
ai_assistant/api.py
ai_assistant/cli.py
ai_assistant/config.py
ai_assistant/extractors.py
ai_assistant/recipes.py
ai_assistant_cli-0.2.0.dist-info/METADATA
ai_assistant_cli-0.2.0.dist-info/WHEEL
ai_assistant_cli-0.2.0.dist-info/entry_points.txt
ai_assistant_cli-0.2.0.dist-info/top_level.txt
ai_assistant_cli-0.2.0.dist-info/RECORD
