Metadata-Version: 2.4
Name: ai-assistant-cli
Version: 0.2.0
Summary: AI-powered CLI assistant using Gemini API
Author: Ruchira
License: MIT
Requires-Dist: requests
Requires-Dist: PyMuPDF
Requires-Dist: python-docx
Requires-Dist: openpyxl
Requires-Dist: python-pptx
Requires-Dist: Pillow
